dbscripts/__init__.py
dbscripts/dbscripts.py
dbscripts/dbwriter.py
dbscripts/utils.py
dbscripts-0.1.42.dist-info/LICENSE
dbscripts-0.1.42.dist-info/METADATA
dbscripts-0.1.42.dist-info/WHEEL
dbscripts-0.1.42.dist-info/top_level.txt
dbscripts-0.1.42.dist-info/RECORD
