Metadata-Version: 2.1
Name: dbscripts
Version: 0.1.42
Summary: A small Python package for handling 'database scripts', including analysis and dependency management.
Home-page: https://github.com/Catterall/dbscripts
Download-URL: https://github.com/Catterall/dbscripts/releases
Author: KCatterall
License: MIT
License-File: LICENSE
Requires-Dist: pyodbc >=5.1.0
